LICENCE
README.md
setup.py
expression_builder/__init__.py
expression_builder/exceptions.py
expression_builder/expression_builder.py
expression_builder/globals.py
expression_builder.egg-info/PKG-INFO
expression_builder.egg-info/SOURCES.txt
expression_builder.egg-info/dependency_links.txt
expression_builder.egg-info/top_level.txt