Metadata-Version: 2.1
Name: expression-builder
Version: 0.0.9
Summary: Django app that does mathematical expression
Home-page: https://github.com/django-advance-utils/expression-builder
Author: Tom Turner
Classifier: Programming Language :: Python :: 3
Classifier: License :: OSI Approved :: MIT License
Classifier: Operating System :: OS Independent
Requires-Python: >=3.7
License-File: LICENCE
